milkjug/__init__.py
milkjug/api.py
milkjug/middleware.py
milkjug/utils.py
milkjug-0.1.1.dist-info/WHEEL
milkjug-0.1.1.dist-info/METADATA
milkjug-0.1.1.dist-info/RECORD
